ids_xs_tools/ImageFunctions.py
ids_xs_tools/OpenCV_to_RAPID.py
ids_xs_tools/Puck.py
ids_xs_tools/QR_Reader.py
ids_xs_tools/__init__.py
ids_xs_tools/config.py
ids_xs_tools/pyueye_example_camera.py
ids_xs_tools/pyueye_example_utils.py
IDS_XS_TOOLS_UiS-0.3.dist-info/LICENSE
IDS_XS_TOOLS_UiS-0.3.dist-info/METADATA
IDS_XS_TOOLS_UiS-0.3.dist-info/WHEEL
IDS_XS_TOOLS_UiS-0.3.dist-info/top_level.txt
IDS_XS_TOOLS_UiS-0.3.dist-info/RECORD
