Metadata-Version: 2.1
Name: IDS-XS-TOOLS-UiS
Version: 0.3
Summary: Image functions for IDS XS camera
Home-page: https://github.com/prinsWindy/ABB-pucks
Author: Ole Christian Handegård
Author-email: ole.hande98@gmail.com
License: UNKNOWN
Platform: UNKNOWN
Classifier: Programming Language :: Python :: 3
Classifier: License :: OSI Approved :: MIT License
Classifier: Operating System :: OS Independent
Requires-Python: >=3.6
Requires-Dist: pyzbar
Requires-Dist: opencv-python
Requires-Dist: pyueye
